trade_mcp/__init__.py
trade_mcp/api/__init__.py
trade_mcp/api/client.py
trade_mcp/api/http_utils.py
trade_mcp/api/market_data.py
trade_mcp/api/trading.py
trade_mcp/server/__init__.py
trade_mcp/server/main.py
trade_mcp/server/mcp_tools.py
trade_mcp-0.1.12.dist-info/METADATA
trade_mcp-0.1.12.dist-info/WHEEL
trade_mcp-0.1.12.dist-info/entry_points.txt
trade_mcp-0.1.12.dist-info/top_level.txt
trade_mcp-0.1.12.dist-info/RECORD
