Metadata-Version: 2.4
Name: trade_mcp
Version: 0.1.12
Summary: Axgrad Trade MCP Server: Unified interface for Binance Futures and Aster APIs via MCP.
Author-email: Axgrad Team <tianyix@saharalabs.ai>
Requires-Python: >=3.10
Requires-Dist: python-binance==1.0.19
Requires-Dist: httpx>=0.27.0
Requires-Dist: uvicorn==0.27.1
Requires-Dist: starlette==0.37.1
Requires-Dist: fastmcp==0.1.0
Requires-Dist: python-dotenv==1.0.1
